Workbook

Sheet Ipotesi
A1: 🐗 TOSCANACCIO — Piano Finanziario 2024-2025
A2: Ghost Kitchen · Via Tito Speri 28, Livorno · S.r.l.
A4: RICAVI – Ipotesi Operative
A5: Scontrino medio delivery/walk-in (€) | B5: 15 | C5: ℹ Media fascia 12-18€ scelto 15€
A6: Ordini/giorno – mese 1 (avvio) | B6: 10 | C6: ℹ Ramp-up iniziale
A7: Ordini/giorno – mese 6 (regime) | B7: 50 | C7: ℹ Target mid 40-60 scelto 50
A8: Giorni operativi/mese | B8: 26 | C8: ℹ 6 giorni/settimana
A9: Commissione piattaforme delivery (%) | B9: 0 | C9: ℹ Delivery proprietario → 0%
A11: COSTI FISSI MENSILI
A12: Affitto (€/mese) | B12: 450
A13: Utilities (luce/gas/acqua) | B13: 300
A14: Connettività + SIM Teltonika | B14: 50
A15: Manutenzione hardware/vending | B15: 80
A16: Assicurazione RC + locale | B16: 100
A17: Contabilità Studio Esposito | B17: 150
A18: Abbonamenti software (FastAPI hosting, ecc.) | B18: 60
A19: Packaging (Pyrex, kraft, ecc.) – fisso mensile | B19: 200
A20: TOTALE COSTI FISSI | B20: =SUM(B12:B19) -> 1390
A22: COSTI VARIABILI
A23: Food cost medio (% su ricavo) | B23: 0.27 | C23: ℹ Media ponderata menu (14%-38%)
A24: Costo rider interno (€/giorno operativo) | B24: 50 | C24: ℹ 1 rider part-time
A25: Materiali consumabili extra (€/mese) | B25: 100 | C25: ℹ Guanti, etichette NFC, ecc.
A27: PERSONALE
A28: Titolare – compenso mensile (€) | B28: 1500
A29: Aiuto cucina – costo mensile lordo (€) | B29: 1200
A30: TOTALE PERSONALE | B30: =SUM(B28:B29) -> 2700
A32: INVESTIMENTO INIZIALE & FINANZIAMENTO
A33: Capitale investito (€) | B33: 45000
A34: Quota attrezzature (hardware/vending) | B34: 28000
A35: Quota allestimento locale | B35: 8000
A36: Quota scorte iniziali e working capital | B36: 5000
A37: Quota riserva liquidità | B37: 4000
A38: Quota ricercata da investitore (€) | B38: 25000
A39: Equity ceduta (%) – da negoziare | B39: 0.2

Sheet P&L Mensile
A1: CONTO ECONOMICO MENSILE — 12 MESI
A2: Valori in €
B3: Gen | C3: Feb | D3: Mar | E3: Apr | F3: Mag | G3: Giu | H3: Lug | I3: Ago | J3: Set | K3: Ott | L3: Nov | M3: Dic | N3: TOTALE
A4: — DRIVER OPERATIVI —
A5: Ordini/giorno (interpolati) | B5: 10 | C5: 18 | D5: 26 | E5: 34 | F5: 42 | G5: 50 | H5: 50 | I5: 50 | J5: 50 | K5: 50 | L5: 50 | M5: 50
A6: Giorni operativi | B6: =Ipotesi!$B$8 -> 26 | C6: =Ipotesi!$B$8 -> 26 | D6: =Ipotesi!$B$8 -> 26 | E6: =Ipotesi!$B$8 -> 26 | F6: =Ipotesi!$B$8 -> 26 | G6: =Ipotesi!$B$8 -> 26 | H6: =Ipotesi!$B$8 -> 26 | I6: =Ipotesi!$B$8 -> 26 | ... M6: =Ipotesi!$B$8 -> 26
A7: Totale ordini mese | B7: =B5*B6 -> 260 | C7: =C5*C6 -> 468 | D7: =D5*D6 -> 676 | E7: =E5*E6 -> 884 | F7: =F5*F6 -> 1092 | G7: =G5*G6 -> 1300 | H7: =H5*H6 -> 1300 | I7: =I5*I6 -> 1300 | ... M7: =M5*M6 -> 1300 | N7: =SUM(B7:M7) -> 12480
A8: Ricavo lordo | B8: =B7*Ipotesi!$B$5 -> 3900 | C8: =C7*Ipotesi!$B$5 -> 7020 | D8: =D7*Ipotesi!$B$5 -> 10140 | E8: =E7*Ipotesi!$B$5 -> 13260 | F8: =F7*Ipotesi!$B$5 -> 16380 | G8: =G7*Ipotesi!$B$5 -> 19500 | H8: =H7*Ipotesi!$B$5 -> 19500 | I8: =I7*Ipotesi!$B$5 -> 19500 | ... M8: =M7*Ipotesi!$B$5 -> 19500 | N8: =SUM(B8:M8) -> 187200
A10: COSTI VARIABILI
A11: Food cost | B11: =B8*Ipotesi!$B$23 -> 1053 | C11: =C8*Ipotesi!$B$23 -> 1895.4 | D11: =D8*Ipotesi!$B$23 -> 2737.8 | E11: =E8*Ipotesi!$B$23 -> 3580.2 | F11: =F8*Ipotesi!$B$23 -> 4422.6 | G11: =G8*Ipotesi!$B$23 -> 5265 | H11: =H8*Ipotesi!$B$23 -> 5265 | I11: =I8*Ipotesi!$B$23 -> 5265 | ... M11: =M8*Ipotesi!$B$23 -> 5265 | N11: =SUM(B11:M11) -> 50544
A12: Costo rider | B12: =Ipotesi!$B$24*Ipotesi!$B$8 -> 1300 | C12: =Ipotesi!$B$24*Ipotesi!$B$8 -> 1300 | D12: =Ipotesi!$B$24*Ipotesi!$B$8 -> 1300 | E12: =Ipotesi!$B$24*Ipotesi!$B$8 -> 1300 | F12: =Ipotesi!$B$24*Ipotesi!$B$8 -> 1300 | G12: =Ipotesi!$B$24*Ipotesi!$B$8 -> 1300 | H12: =Ipotesi!$B$24*Ipotesi!$B$8 -> 1300 | I12: =Ipotesi!$B$24*Ipotesi!$B$8 -> 1300 | ... M12: =Ipotesi!$B$24*Ipotesi!$B$8 -> 1300 | N12: =SUM(B12:M12) -> 15600
A13: Consumabili | B13: =Ipotesi!$B$25 -> 100 | C13: =Ipotesi!$B$25 -> 100 | D13: =Ipotesi!$B$25 -> 100 | E13: =Ipotesi!$B$25 -> 100 | F13: =Ipotesi!$B$25 -> 100 | G13: =Ipotesi!$B$25 -> 100 | H13: =Ipotesi!$B$25 -> 100 | I13: =Ipotesi!$B$25 -> 100 | ... M13: =Ipotesi!$B$25 -> 100 | N13: =SUM(B13:M13) -> 1200
A14: TOT. Costi Variabili | B14: =SUM(B11:B13) -> 2453 | C14: =SUM(C11:C13) -> 3295.4 | D14: =SUM(D11:D13) -> 4137.8 | E14: =SUM(E11:E13) -> 4980.2 | F14: =SUM(F11:F13) -> 5822.6 | G14: =SUM(G11:G13) -> 6665 | H14: =SUM(H11:H13) -> 6665 | I14: =SUM(I11:I13) -> 6665 | ... N14: =SUM(N11:N13) -> 67344
A16: COSTI FISSI
A17: Personale (titolare + aiuto) | B17: =Ipotesi!$B$30 -> 2700 | C17: =Ipotesi!$B$30 -> 2700 | D17: =Ipotesi!$B$30 -> 2700 | E17: =Ipotesi!$B$30 -> 2700 | F17: =Ipotesi!$B$30 -> 2700 | G17: =Ipotesi!$B$30 -> 2700 | H17: =Ipotesi!$B$30 -> 2700 | I17: =Ipotesi!$B$30 -> 2700 | ... M17: =Ipotesi!$B$30 -> 2700 | N17: =SUM(B17:M17) -> 32400
A18: Altri costi fissi | B18: =Ipotesi!$B$20 -> 1390 | C18: =Ipotesi!$B$20 -> 1390 | D18: =Ipotesi!$B$20 -> 1390 | E18: =Ipotesi!$B$20 -> 1390 | F18: =Ipotesi!$B$20 -> 1390 | G18: =Ipotesi!$B$20 -> 1390 | H18: =Ipotesi!$B$20 -> 1390 | I18: =Ipotesi!$B$20 -> 1390 | ... M18: =Ipotesi!$B$20 -> 1390 | N18: =SUM(B18:M18) -> 16680
A19: TOT. Costi Fissi | B19: =SUM(B17:B18) -> 4090 | C19: =SUM(C17:C18) -> 4090 | D19: =SUM(D17:D18) -> 4090 | E19: =SUM(E17:E18) -> 4090 | F19: =SUM(F17:F18) -> 4090 | G19: =SUM(G17:G18) -> 4090 | H19: =SUM(H17:H18) -> 4090 | I19: =SUM(I17:I18) -> 4090 | ... N19: =SUM(N17:N18) -> 49080
A21: EBITDA | B21: =B8-B14-B19 -> -2643 | C21: =C8-C14-C19 -> -365.4 | D21: =D8-D14-D19 -> 1912.2 | E21: =E8-E14-E19 -> 4189.8 | F21: =F8-F14-F19 -> 6467.4 | G21: =G8-G14-G19 -> 8745 | H21: =H8-H14-H19 -> 8745 | I21: =I8-I14-I19 -> 8745 | ... N21: =N8-N14-N19 -> 70776
A22: Margine EBITDA % | B22: =IF(B8>0,B21/B8,0) -> -0.67769231 | C22: =IF(C8>0,C21/C8,0) -> -0.052051282 | D22: =IF(D8>0,D21/D8,0) -> 0.18857988 | E22: =IF(E8>0,E21/E8,0) -> 0.31597285 | F22: =IF(F8>0,F21/F8,0) -> 0.39483516 | G22: =IF(G8>0,G21/G8,0) -> 0.44846154 | H22: =IF(H8>0,H21/H8,0) -> 0.44846154 | I22: =IF(I8>0,I21/I8,0) -> 0.44846154 | ... N22: =IF(N8>0,N21/N8,0) -> 0.37807692

Sheet Cash Flow
A1: FLUSSO DI CASSA MENSILE
B2: Gen | C2: Feb | D2: Mar | E2: Apr | F2: Mag | G2: Giu | H2: Lug | I2: Ago | J2: Set | K2: Ott | L2: Nov | M2: Dic | N2: TOTALE
A3: Saldo iniziale cassa
A4: Saldo iniziale | B4: =Ipotesi!$B$37 -> 4000 | C4: =B7 -> 1357 | D4: =C7 -> 991.6 | E4: =D7 -> 2903.8 | F4: =E7 -> 7093.6 | G4: =F7 -> 13561 | H4: =G7 -> 22306 | I4: =H7 -> 31051 | J4: =I7 -> 39796 | ... M4: =L7 -> 66031
A5: (+) Incassi delivery/walk-in | B5: ='P&L Mensile'!B8 -> 3900 | C5: ='P&L Mensile'!C8 -> 7020 | D5: ='P&L Mensile'!D8 -> 10140 | E5: ='P&L Mensile'!E8 -> 13260 | F5: ='P&L Mensile'!F8 -> 16380 | G5: ='P&L Mensile'!G8 -> 19500 | H5: ='P&L Mensile'!H8 -> 19500 | I5: ='P&L Mensile'!I8 -> 19500 | ... M5: ='P&L Mensile'!M8 -> 19500 | N5: =SUM(B5:M5) -> 187200
A6: (-) Totale costi (var+fissi) | B6: ='P&L Mensile'!B14+'P&L Mensile'!B19 -> 6543 | C6: ='P&L Mensile'!C14+'P&L Mensile'!C19 -> 7385.4 | D6: ='P&L Mensile'!D14+'P&L Mensile'!D19 -> 8227.8 | E6: ='P&L Mensile'!E14+'P&L Mensile'!E19 -> 9070.2 | F6: ='P&L Mensile'!F14+'P&L Mensile'!F19 -> 9912.6 | G6: ='P&L Mensile'!G14+'P&L Mensile'!G19 -> 10755 | H6: ='P&L Mensile'!H14+'P&L Mensile'!H19 -> 10755 | I6: ='P&L Mensile'!I14+'P&L Mensile'!I19 -> 10755 | ... M6: ='P&L Mensile'!M14+'P&L Mensile'!M19 -> 10755 | N6: =SUM(B6:M6) -> 116424
B7: =B4+B5-B6 -> 1357 | C7: =C4+C5-C6 -> 991.6 | D7: =D4+D5-D6 -> 2903.8 | E7: =E4+E5-E6 -> 7093.6 | F7: =F4+F5-F6 -> 13561 | G7: =G4+G5-G6 -> 22306 | H7: =H4+H5-H6 -> 31051 | I7: =I4+I5-I6 -> 39796 | ... M7: =M4+M5-M6 -> 74776 | N7: =M7 -> 74776

Sheet Break Even
A1: ANALISI BREAK-EVEN
A3: Costi fissi mensili totali | B3: =Ipotesi!B20+Ipotesi!B30 -> 4090
A4: Scontrino medio netto (€) | B4: =Ipotesi!B5 -> 15
A5: Food cost per ordine (€) | B5: =Ipotesi!B5*Ipotesi!B23 -> 4.05
A6: Costo rider per ordine (€) | B6: =Ipotesi!B24/Ipotesi!B8 -> 1.9230769
A7: Contribuzione unitaria (€) | B7: =B4-B5-B6 -> 9.0269231
A8: Margine contribuzione % | B8: =B7/B4 -> 0.60179487
A10: Break-even ordini/mese | B10: =ROUNDUP(B3/B7,0) -> 454
A11: Break-even ordini/giorno | B11: =ROUNDUP(B10/Ipotesi!$B$8,0) -> 18
A12: Break-even ricavo mensile (€) | B12: =B10*B4 -> 6810
A14: Ordini/giorno a regime (target) | B14: =Ipotesi!B7 -> 50
A15: Ricavo mensile a regime (€) | B15: =B14*Ipotesi!B8*B4 -> 19500
A16: Margine EBITDA mensile a regime (€) | B16: =B15*(1-Ipotesi!B23)-Ipotesi!B24*Ipotesi!B8-Ipotesi!B25-Ipotesi!B20-Ipotesi!B30 -> 8745
A18: Mese stimato raggiungimento break-even | B18: 4
A19: ROI investimento (12 mesi) | B19: ='P&L Mensile'!N21/Ipotesi!B33 -> 1.5728

Sheet Menu & Margini
A1: MENU TOSCANACCIO — ANALISI MARGINI
A2: Codice | B2: Nome piatto | C2: Categoria | D2: Prezzo € | E2: Food Cost % | F2: Margine € | G2: Canali | H2: Firma
A3: TOS-001 | B3: Cacciucco alla livornese | C3: Zuppa di pesce | D3: 13 | E3: 0.38 | F3: =D3*(1-E3) -> 8.06 | G3: walk-in | H3: ⭐
A4: TOS-002 | B4: Cinghiale in salmì | C4: Secondo di carne | D4: 9 | E4: 0.33 | F4: =D4*(1-E4) -> 6.03 | G4: walk-in, delivery | H4: ⭐
A5: TOS-003 | B5: Peposo dell'Impruneta | C5: Secondo di carne | D5: 8 | E5: 0.3 | F5: =D5*(1-E5) -> 5.6 | G5: walk-in, delivery | H5: ⭐
A6: TOS-004 | B6: Lampredotto in umido | C6: Quinto quarto | D6: 7.5 | E6: 0.22 | F6: =D6*(1-E6) -> 5.85 | G6: walk-in | H6: ⭐
A7: TOS-005 | B7: Ragù di chianina al cucchiaio | C7: Piatto unico | D7: 7 | E7: 0.28 | F7: =D7*(1-E7) -> 5.04 | G7: walk-in, delivery
A8: TOS-006 | B8: Polpette al sugo della mamma | C8: Secondo di carne | D8: 7 | E8: 0.27 | F8: =D8*(1-E8) -> 5.11 | G8: walk-in, delivery, vending
A9: TOS-007 | B9: Ribollita della nonna | C9: Zuppa | D9: 6.5 | E9: 0.24 | F9: =D9*(1-E9) -> 4.94 | G9: walk-in, delivery | H9: ⭐🌿
A10: TOS-008 | B10: Fagioli all'uccelletto con salsiccia | C10: Piatto unico | D10: 6.5 | E10: 0.25 | F10: =D10*(1-E10) -> 4.875 | G10: walk-in, delivery, vending
A11: TOS-009 | B11: Zuppa di farro della Garfagnana | C11: Zuppa | D11: 6 | E11: 0.21 | F11: =D11*(1-E11) -> 4.74 | G11: walk-in, delivery, vending | H11: 🌿
A12: TOS-010 | B12: Pappa al pomodoro | C12: Zuppa | D12: 5.5 | E12: 0.19 | F12: =D12*(1-E12) -> 4.455 | G12: walk-in, delivery, vending | H12: ⭐🌿
A13: TOS-011 | B13: Cecìna livornese | C13: Street food | D13: 3.5 | E13: 0.14 | F13: =D13*(1-E13) -> 3.01 | G13: walk-in, vending | H13: ⭐🌿
A14: TOS-012 | B14: Cantucci con Vin Santo | C14: Dolce | D14: 3 | E14: 0.16 | F14: =D14*(1-E14) -> 2.52 | G14: walk-in, delivery, vending
B15: MEDIA PONDERATA / TOTALE | D15: =AVERAGE(D3:D14) -> 6.875 | E15: =AVERAGE(E3:E14) -> 0.2475 | F15: =AVERAGE(F3:F14) -> 5.0191667
